Metadata-Version: 1.0
Name: SeleniumAuthProxy
Version: 0.0
Summary: Library for installing in Selenium proxy servers with authorization
Home-page: UNKNOWN
Author: UNKNOWN
Author-email: mart-iden@rambler.ru
License: UNKNOWN
Platform: UNKNOWN
